pycocotools-stubs/__init__.pyi
pycocotools-stubs/coco.pyi
pycocotools-stubs/coco_types.pyi
pycocotools-stubs/cocoeval.pyi
pycocotools-stubs/mask.pyi
pycocotools-stubs/py.typed
pycocotools_stubs-0.1.1.dist-info/METADATA
pycocotools_stubs-0.1.1.dist-info/WHEEL
pycocotools_stubs-0.1.1.dist-info/licenses/LICENSE
pycocotools_stubs-0.1.1.dist-info/RECORD
