Metadata-Version: 2.1
Name: pycocotools-stubs
Version: 0.1.1
Summary: Unofficial stubs for the pycocotools package.
Project-URL: Homepage, https://github.com/hoel-bagard/pycocotools-stubs
Project-URL: Bug Tracker, https://github.com/hoel-bagard/pycocotools-stubs/issues
Author: Bagard Hoel
License: MIT
License-File: LICENSE
Keywords: pycocotools,stubs
Classifier: Intended Audience :: Developers
Classifier: License :: OSI Approved :: MIT License
Classifier: Operating System :: OS Independent
Classifier: Programming Language :: Python
Classifier: Programming Language :: Python :: 3.8
Classifier: Programming Language :: Python :: 3.9
Classifier: Programming Language :: Python :: 3.10
Classifier: Programming Language :: Python :: 3.11
Classifier: Programming Language :: Python :: Implementation :: CPython
Requires-Python: >=3.8
Requires-Dist: pycocotools>=2.0.6
Provides-Extra: build
Requires-Dist: hatch; extra == 'build'
Provides-Extra: dev
Requires-Dist: pip-tools; extra == 'dev'
Requires-Dist: pre-commit; extra == 'dev'
Requires-Dist: pyright; extra == 'dev'
Requires-Dist: ruff; extra == 'dev'
